OceanLab/dyn.py
OceanLab/eof.py
OceanLab/oa.py
OceanLab/utils.py
OceanLab-0.1.0.dist-info/LICENSE.txt
OceanLab-0.1.0.dist-info/METADATA
OceanLab-0.1.0.dist-info/WHEEL
OceanLab-0.1.0.dist-info/top_level.txt
OceanLab-0.1.0.dist-info/RECORD
