Metadata-Version: 2.1
Name: OceanLab
Version: 0.1.0
Summary: Python functions for Physical Oceanography
Home-page: https://github.com/iuryt/OceanLab
Author: Iury T. Simoes-Sousa
Author-email: simoesiury@gmail.com
License: The MIT License (MIT)        
Download-URL: https://pypi.python.org/pypi/OceanLab
Platform: UNKNOWN
Classifier: Programming Language :: Python :: 3
Classifier: Programming Language :: Python :: 3.6
Classifier: Programming Language :: Python :: 3.7
Classifier: License :: OSI Approved :: MIT License
Classifier: Operating System :: OS Independent
License-File: LICENSE.txt
Requires-Dist: seawater (~=3.3)
Requires-Dist: numpy (~=1.18)
Requires-Dist: scipy (~=1.6)
Requires-Dist: xarray (~=0.18)
Requires-Dist: dask (~=2021.06)
Requires-Dist: dask[distributed] (~=2021.06)
